<xml xmlns="https://developers.google.com/blockly/xml"><block type="component_event" id="j_y}=0%Vjr2@/b8x.QXO" x="138" y="74"><mutation xmlns="http://www.w3.org/1999/xhtml" component_id="a35ed6bc-3379-4aee-93f2-9e10325284c0" component_name="buttonTest" component_type="Button" parent_id="undefined" event_id="Click" was_updated="true"/><field name="component_id">a35ed6bc-3379-4aee-93f2-9e10325284c0</field><field name="event_id">Click</field><statement name="input_do"><block type="oauth_sign_out_from_google_advanced" id="MIeCzo-Y^$A5vsS:)yke" inline="false"><mutation xmlns="http://www.w3.org/1999/xhtml" show_callback_params="true" callback_params_added="true"/><value name="CALLBACK_PARAM0"><block type="callback_arg" id="tD}C:OUs,=kbjbW25H1m"><mutation xmlns="http://www.w3.org/1999/xhtml" tooltip="" language_neutral_name="error" arg_name_trans_key="blocks.oauth.sign_out_from_google.error" old_arg_name="error"/></block></value><statement name="DO"><block type="controls_if" id="{.EJb9TrF9(!U:g0)BSb"><mutation else="1"/><value name="IF0"><block type="callback_arg" id="lS(D9nn`=Tt1#Q~mDjCD"><mutation xmlns="http://www.w3.org/1999/xhtml" tooltip="" language_neutral_name="error" arg_name_trans_key="blocks.oauth.sign_out_from_google.error" old_arg_name="error" is_detached_parameter="true"/></block></value><statement name="ELSE"><block type="controls_navigate_new" id=":C:W5JsXZ+HTQ{gKryDj"><value name="COMPONENT"><shadow type="any_component_component_dropdown" id="^tH^VbqoaS^9QlF3tE:e"><mutation xmlns="http://www.w3.org/1999/xhtml" component_id="Welcome Screen" component_types_to_include="[&quot;Screen&quot;]"/><field name="component_id">6ec24246-6a7f-4f44-a084-120fab1d711b</field></shadow></value></block></statement></block></statement></block></statement></block><block type="component_event" id="iA!y4T_sN~=m?z9b2M9p" x="562" y="138"><mutation xmlns="http://www.w3.org/1999/xhtml" component_id="e28f73c7-f1c0-4079-86eb-d3b5be3c58c8" component_name="Back2" component_type="Button" parent_id="undefined" event_id="Click" was_updated="true"/><field name="component_id">e28f73c7-f1c0-4079-86eb-d3b5be3c58c8</field><field name="event_id">Click</field><statement name="input_do"><block type="controls_navigate_new" id="_=33e73sVs!`-2?aA)?A"><value name="COMPONENT"><shadow type="any_component_component_dropdown" id="yLKAf6etW1`:CxA/!L_T"><mutation xmlns="http://www.w3.org/1999/xhtml" component_id="Profile" component_types_to_include="[&quot;Screen&quot;]"/><field name="component_id">d9ba9376-9e5c-4d57-8a52-dae16d8dcbdf</field></shadow></value></block></statement></block></xml>