<xml xmlns="https://developers.google.com/blockly/xml"><block type="component_event" id="Xiw95=k)+`FC1Y#$8Y;S" x="18" y="-6"><mutation xmlns="http://www.w3.org/1999/xhtml" component_id="3a48dcc1-9ace-4052-b0ac-b3dfd26b74a4" component_name="User_Feed" component_type="Screen" parent_id="undefined" event_id="Opens" was_updated="true"/><field name="component_id">3a48dcc1-9ace-4052-b0ac-b3dfd26b74a4</field><field name="event_id">Opens</field><statement name="input_do"><block type="setter" id="D+h}^g8rYGH)~B0I:nXt"><mutation xmlns="http://www.w3.org/1999/xhtml" component_name="ProfileImage1"/><field name="component_id">e79c79f9-b306-4a30-b3d8-ac5d0d4bbbfb</field><field name="field_name">Picture</field><value name="field_value"><shadow type="asset_get" id="?Q)pJOHAvkyqk6lMoCSg"><mutation xmlns="http://www.w3.org/1999/xhtml" previous_asset_name="default_profile_400x400.png" previous_asset_value="65f8c7904904614c5984f382"/><field name="ASSET">65f8c7904904614c5984f382</field></shadow></value></block></statement></block><block type="variables_def" id="ogds3mFG550iFPsQwRLA" x="659" y="-2"><mutation xmlns="http://www.w3.org/1999/xhtml" no_input="true" variable_uuid="498740fb-190a-489b-b900-4e474e89ebe9" variable_name="feed-ctr" variable_scope="STORED"/><field name="SCOPE">STORED</field><field name="NAME">feed-ctr</field></block><block type="variables_def" id="mWIYcbKnHN8~Y9F|=yPm" x="19" y="77"><mutation xmlns="http://www.w3.org/1999/xhtml" no_input="false" variable_uuid="9e564abd-2375-4449-9e11-8faaf25d5ed3" variable_name="feed" variable_scope="APP"/><field name="SCOPE">APP</field><field name="NAME">feed</field><value name="VALUE"><block type="lists_create_empty" id="`h[TYKnzG:C,WHnJ@[Pn"/></value></block><block type="component_event" id="AByC|L{XSjJ+OD9!rM=-" x="717" y="42"><mutation xmlns="http://www.w3.org/1999/xhtml" component_id="3a48dcc1-9ace-4052-b0ac-b3dfd26b74a4" component_name="User_Feed" component_type="Screen" parent_id="undefined" event_id="Opens" was_updated="true"/><field name="component_id">3a48dcc1-9ace-4052-b0ac-b3dfd26b74a4</field><field name="event_id">Opens</field><statement name="input_do"><block type="variables_change_by_dynamic" id="tF/3ownd9$sN$JZH/u9q"><field name="SCOPE">CLOUD</field><value name="NAME"><shadow type="text" id="?g=oE(B%z/$sJ7Nd2nSV"><field name="TEXT">userfeedViews</field></shadow></value><value name="DELTA"><shadow type="math_number" id="+nS[PF1|c3I9p2xC~[KQ"><field name="NUM">1</field></shadow></value><next><block type="controls_if" id="Rg2kP=a/yy/{t#OGB+Ga"><value name="IF0"><block type="logic_compare" id="gu7D?5aYm.0nEV?v%IgV"><field name="OP">EQ</field><value name="A"><block type="variables_get" id="(i/1I3ED{J*8]qEs)9Tk"><mutation xmlns="http://www.w3.org/1999/xhtml" saved_name="stored variable feed-ctr"/><field name="VAR">498740fb-190a-489b-b900-4e474e89ebe9</field></block></value><value name="B"><block type="logic_null" id="csMLya6,xny;v!su.j/}"/></value></block></value><statement name="DO0"><block type="variables_set" id="m|8{Mu8`EW9?=2Ugy|qH"><mutation xmlns="http://www.w3.org/1999/xhtml" saved_name="stored variable feed-ctr"/><field name="VAR">498740fb-190a-489b-b900-4e474e89ebe9</field><value name="VALUE"><block type="logic_boolean" id="Lu^Ar@A;m.u^%uy9QKn?"><field name="BOOL">TRUE</field></block></value><next><block type="variables_set_dynamic" id="%|,KkSF#FSikCmbdp]WG"><field name="SCOPE">CLOUD</field><value name="NAME"><shadow type="text" id="*xupGO%w%E4`t%D1xG]j"><field name="TEXT">name</field></shadow><block type="text_join" id="f4qCTZK]yb^e9},n}lBt"><mutation items="2"/><value name="ADD0"><block type="variables_get" id="24;Bh;L1gA#Kl69[,z9("><mutation xmlns="http://www.w3.org/1999/xhtml" saved_name="app variable userID"/><field name="VAR">e57a164c-c6f3-465a-a981-6b0ce8a8282d</field></block></value><value name="ADD1"><block type="text" id="3T.BGMY1gd$mB^2kF=;q"><field name="TEXT">/CTR</field></block></value></block></value><value name="VALUE"><block type="math_number" id="Y}ha~(P{yPt.Oj@z}DD%"><field name="NUM">4</field></block></value></block></next></block></statement></block></next></block></statement></block><block type="variables_def" id="e]NT1rs`b.!}T*D6xQCq" x="27" y="111"><mutation xmlns="http://www.w3.org/1999/xhtml" no_input="false" variable_uuid="45dce41c-988f-4c08-bf7d-c14275be6f49" variable_name="idString" variable_scope="APP"/><field name="SCOPE">APP</field><field name="NAME">idString</field><value name="VALUE"><block type="text" id="OZ4`IA~pDWDt.#3_O=66"><field name="TEXT"/></block></value></block><block type="variables_def" id="ZXJeG~+m^Y_a,XLZ{qAJ" x="25" y="141"><mutation xmlns="http://www.w3.org/1999/xhtml" no_input="false" variable_uuid="c377171d-c807-4570-aa8a-2db26ba966a8" variable_name="feed_text" variable_scope="APP"/><field name="SCOPE">APP</field><field name="NAME">feed_text</field><value name="VALUE"><block type="text" id="y[Q6E#LOpCz]9FDBG.Zz"><field name="TEXT"/></block></value></block><block type="component_event" id="Ou?BAK*g/ymK9DIc/)}I" x="22" y="173"><mutation xmlns="http://www.w3.org/1999/xhtml" component_id="8bdf3260-5a94-451f-bc1e-b0eca0e9127c" component_name="feed_button" component_type="Button" parent_id="undefined" event_id="Click" was_updated="true"/><field name="component_id">8bdf3260-5a94-451f-bc1e-b0eca0e9127c</field><field name="event_id">Click</field><statement name="input_do"><block type="variables_set" id="O~*d,2cN/U/l[;/MONjw"><mutation xmlns="http://www.w3.org/1999/xhtml" saved_name="app variable idString"/><field name="VAR">45dce41c-988f-4c08-bf7d-c14275be6f49</field><value name="VALUE"><block type="text_join" id="D.V1hRE)0z+JeC#:^0J}"><mutation items="3"/><value name="ADD0"><block type="text" id="-;P{OVHFV!CD-@BYkJQT"><field name="TEXT">"</field></block></value><value name="ADD1"><block type="variables_get" id="[zA5jTGQH9j}pJq5xrt|"><mutation xmlns="http://www.w3.org/1999/xhtml" saved_name="app variable userID"/><field name="VAR">e57a164c-c6f3-465a-a981-6b0ce8a8282d</field></block></value><value name="ADD2"><block type="text" id="f^EiZzlVjl.^alJSeeH["><field name="TEXT">"</field></block></value></block></value><next><block type="variables_set" id="@-bfyp#T7G-RF1ZW)er!"><mutation xmlns="http://www.w3.org/1999/xhtml" saved_name="app variable feed_text"/><field name="VAR">c377171d-c807-4570-aa8a-2db26ba966a8</field><value name="VALUE"><block type="text_join" id="^,r[A8)c.$5#R(w;$nvO"><mutation items="3"/><value name="ADD0"><block type="text" id="X?kpHN/Xn+GkG^1OVlUk"><field name="TEXT">"</field></block></value><value name="ADD1"><block type="set_get" id="PM@WW2gYyg|C4|PtuuP:"><mutation xmlns="http://www.w3.org/1999/xhtml" component_name="feed_input"/><field name="component_id">4bca56cd-04a7-4eaf-a0f5-27c26bd6a50f</field><field name="field_name">Text</field></block></value><value name="ADD2"><block type="text" id="+FO3@Va-asnAf}Bvx0Eq"><field name="TEXT">"</field></block></value></block></value><next><block type="controls_if" id="?,ZWSfPYi[!{@_f2io3/"><mutation else="1"/><value name="IF0"><block type="logic_compare" id="(a?dM,cN]-RuYQs]l:Pr"><field name="OP">EQ</field><value name="A"><block type="set_get" id="X4`MX92x2D+pm!Trk^tk"><mutation xmlns="http://www.w3.org/1999/xhtml" component_name="feed_input"/><field name="component_id">4bca56cd-04a7-4eaf-a0f5-27c26bd6a50f</field><field name="field_name">Text</field></block></value><value name="B"><block type="logic_null" id="`s@S5^=?FGu4(SG~VgkQ"/></value></block></value><statement name="ELSE"><block type="setter" id="E~*`c,e20k70r`X5}QA_"><mutation xmlns="http://www.w3.org/1999/xhtml" component_name="Store_Feed_Post"/><field name="component_id">570af70b-b6dc-4e26-b567-dc840e0c29fc</field><field name="field_name">Body</field><value name="field_value"><block type="text_join" id="X9{)a)$t,|gJGl]a4GIH"><mutation items="5"/><value name="ADD0"><block type="text" id="|chq*@^4w6QNCbcVzS!-"><field name="TEXT">{"userId": </field></block></value><value name="ADD1"><block type="variables_get" id="A`wKi,$pv3FQpMBUg)}L"><mutation xmlns="http://www.w3.org/1999/xhtml" saved_name="app variable idString"/><field name="VAR">45dce41c-988f-4c08-bf7d-c14275be6f49</field></block></value><value name="ADD2"><block type="text" id="IE,^`C:Lg!xu_j=)2B!a"><field name="TEXT">, "inputString": </field></block></value><value name="ADD3"><block type="variables_get" id="|%^c*$tRGw)NO3D,twXn"><mutation xmlns="http://www.w3.org/1999/xhtml" saved_name="app variable feed_text"/><field name="VAR">c377171d-c807-4570-aa8a-2db26ba966a8</field></block></value><value name="ADD4"><block type="text" id="M{ovC@SCzrpKOTy?%pz,"><field name="TEXT">}</field></block></value></block></value><next><block type="caller" id="+?;EK1E9nbqIgV+25t.!" inline="false"><mutation xmlns="http://www.w3.org/1999/xhtml" component_name="Store_Feed_Post" component_id="570af70b-b6dc-4e26-b567-dc840e0c29fc" component_type="Web API" function_name="Post" was_updated="true"/><field name="component_id">570af70b-b6dc-4e26-b567-dc840e0c29fc</field><field name="function_name">Post</field><value name="c_arg0"><block type="callback_arg" id="Hi*y(iF;pT*^=N#WZObH"><mutation xmlns="http://www.w3.org/1999/xhtml" tooltip="Pull out this block to reference this output of the Post method once it obtains its result(s). Note that this block should only be used in the 'then do' section below." language_neutral_name="response" arg_name_trans_key="blocks.Web API.response" old_arg_name="response"/></block></value><value name="c_arg1"><block type="callback_arg" id="c_blk1"><mutation xmlns="http://www.w3.org/1999/xhtml" tooltip="Pull out this block to reference this output of the Post method once it obtains its result(s). Note that this block should only be used in the 'then do' section below." language_neutral_name="status" arg_name_trans_key="blocks.Web API.status" old_arg_name="status"/></block></value><value name="c_arg2"><block type="callback_arg" id="++yKba7#^,}Wu9@Q.7g?"><mutation xmlns="http://www.w3.org/1999/xhtml" tooltip="Pull out this block to reference this output of the Post method once it obtains its result(s). Note that this block should only be used in the 'then do' section below." language_neutral_name="error" arg_name_trans_key="blocks.Web API.error" old_arg_name="error"/></block></value><statement name="callback"><shadow type="callback_block" id="c_blk"><mutation xmlns="http://www.w3.org/1999/xhtml" placeholder="when Post is done" tooltip="Insert code here to be executed after results have been obtained from the Post method call."/></shadow><block type="controls_if" id="4j0#Jx4$;a-xEi2^.E]4"><mutation else="1"/><value name="IF0"><block type="callback_arg" id="@e7+c=lv*!)#Sx7wj|H9"><mutation xmlns="http://www.w3.org/1999/xhtml" tooltip="Pull out this block to reference this output of the Get method once it obtains its result(s). Note that this block should only be used in the 'then do' section below." language_neutral_name="error" arg_name_trans_key="blocks.Web API.error" old_arg_name="error" is_detached_parameter="true"/></block></value><statement name="ELSE"><block type="setter" id="!Knz6;.grYeXh_J_NUi~"><mutation xmlns="http://www.w3.org/1999/xhtml" component_name="feed_label"/><field name="component_id">838df6ae-4d0b-4a98-95cb-7077384523dd</field><field name="field_name">Text</field><value name="field_value"><shadow type="text" id="S4M8f%eCb)2B@tQ34|IC"><field name="TEXT">Label</field></shadow><block type="callback_arg" id="@C~h*S]wAv}xsS6i}l6{"><mutation xmlns="http://www.w3.org/1999/xhtml" tooltip="Pull out this block to reference this output of the Post method once it obtains its result(s). Note that this block should only be used in the 'then do' section below." language_neutral_name="response" arg_name_trans_key="blocks.Web API.response" old_arg_name="response" is_detached_parameter="true"/></block></value></block></statement></block></statement></block></next></block></statement></block></next></block></next></block></statement></block><block type="component_event" id="0d7_GMr@6kc;2EUUifw1" x="890" y="339"><mutation xmlns="http://www.w3.org/1999/xhtml" component_id="d5b4091b-e1b8-4926-9d76-d4295bba96c9" component_name="Button3" component_type="Button" parent_id="undefined" event_id="Click" was_updated="true"/><field name="component_id">d5b4091b-e1b8-4926-9d76-d4295bba96c9</field><field name="event_id">Click</field><statement name="input_do"><block type="controls_navigate_new" id="6IE$t2A{;^Ib}-~a@l*S"><value name="COMPONENT"><shadow type="any_component_component_dropdown" id="Wm7Dk?z[*1|B4J;;Ajm="><mutation xmlns="http://www.w3.org/1999/xhtml" component_id="Profile" component_types_to_include="[&quot;Screen&quot;]"/><field name="component_id">d9ba9376-9e5c-4d57-8a52-dae16d8dcbdf</field></shadow></value></block></statement></block></xml>